catastro_to_mongodb.py
catastro_to_mongodb-1.0.2.dist-info/LICENSE
catastro_to_mongodb-1.0.2.dist-info/METADATA
catastro_to_mongodb-1.0.2.dist-info/WHEEL
catastro_to_mongodb-1.0.2.dist-info/entry_points.txt
catastro_to_mongodb-1.0.2.dist-info/top_level.txt
catastro_to_mongodb-1.0.2.dist-info/RECORD
