Metadata-Version: 2.1
Name: catastro-to-mongodb
Version: 1.0.2
Summary: Migration Script from Catastro files ( Catalog CP Backup - dBASE IV ) to Mongodb
Home-page: https://github.com/dcervantes/catastro-to-mongodb
Author: David Cervantes Caballero
Author-email: david.cervantes.caballero@gmail.com
License: UNKNOWN
Platform: UNKNOWN
Classifier: Intended Audience :: Developers
Classifier: Natural Language :: Spanish
Classifier: Programming Language :: Python :: 3
Classifier: License :: OSI Approved :: MIT License
Classifier: Operating System :: OS Independent
Classifier: Environment :: Console
Requires-Python: >=3.6
Requires-Dist: click
Requires-Dist: pymongo
